<?xml version="1.0" encoding="UTF-8"?>
<StructureDefinition xmlns="http://hl7.org/fhir" xmlns:xsi="http://www.w3.org/2001/XMLSchema-instance" xsi:schemaLocation="http://hl7.org/fhir ../../input-cache/schemas/R5/fhir-single.xsd">
	<id value="LogicalExample"/>
	<url value="http://hl7.org/fhir/test/multi-lang/StructureDefinition/LogicalExample"/>
	<name value="ExampleLogicalStructureDefinition"/>
	<title value="Example Logical Structure Definition"/>
	<status value="draft"/>
	<publisher value="HL7 Tooling group"/>
	<description value="Example Logical Structure Definition Instance"/>
	<fhirVersion value="5.0.0"/>
	<kind value="logical"/>
	<abstract value="false"/>
	<type value="http://hl7.org/fhir/test/multi-lang/StructureDefinition/LogicalExample"/>
	<baseDefinition value="http://hl7.org/fhir/StructureDefinition/Base"/>
	<derivation value="specialization"/>
	<differential>
		<element id="LogicalExample">
		<path value="LogicalExample"/>
      <short value="Example Logical Structure Definition"/>
      <definition value="Example Logical Structure Definition Instance"/>
    </element>
    <element id="LogicalExample.foo">
      <path value="LogicalExample.foo"/>
      <short value="Some element"/>
      <definition value="A data element"/>
      <min value="0"/>
      <max value="1"/>
      <type>
        <code value="string"/>
      </type>
    </element>
    <element id="LogicalExample.foo.bar">
      <path value="LogicalExample.foo.bar"/>
      <code>
        <system value="http://snomed.info/sct"/>
        <code value="12345"/>
        <display value="Some SNOMED concept"/>
      </code>
      <short value="A child element"/>
      <definition value="A sub-element"/>
      <comment value="This element is to be used when the parent element doesn't provide all details"/>
      <requirements value="This element is required because most often parents don't explain why"/>
      <min value="0"/>
      <max value="1"/>
      <type>
        <code value="string"/>
      </type>
      <constraint>
        <key value="should-be-under-50-chars"/>
        <severity value="warning"/>
        <human value="Length SHOULD be &lt;50 for data minimization."/>
        <expression value="$this.length() &lt; 50')"/>
        <source value="http://example.org/StructureDefinition/LogicalExample"/>
      </constraint>
      <isSummary value="true"/>
    </element>
  </differential>
</StructureDefinition>
